enabler_keitaro_inc/__init__.py
enabler_keitaro_inc/commands/__init__.py
enabler_keitaro_inc/commands/cmd_apps.py
enabler_keitaro_inc/commands/cmd_kind.py
enabler_keitaro_inc/commands/cmd_platform.py
enabler_keitaro_inc/commands/cmd_preflight.py
enabler_keitaro_inc/commands/cmd_setup.py
enabler_keitaro_inc/commands/cmd_version.py
enabler_keitaro_inc/commands/enabler_completion.sh
enabler_keitaro_inc/enabler.py
enabler_keitaro_inc/helpers/__init__.py
enabler_keitaro_inc/helpers/git.py
enabler_keitaro_inc/helpers/kind.py
enabler_keitaro_inc/helpers/kube.py
enabler_keitaro_inc/type/__init__.py
enabler_keitaro_inc/type/semver.py
enabler_keitaro_inc-0.1.2.dist-info/LICENSE.md
enabler_keitaro_inc-0.1.2.dist-info/METADATA
enabler_keitaro_inc-0.1.2.dist-info/WHEEL
enabler_keitaro_inc-0.1.2.dist-info/RECORD
