Metadata-Version: 2.1
Name: enabler_keitaro_inc
Version: 0.1.2
Summary: Enabler is a CLI application built for making life easier when working on microservice-based applications. Through this package we can create, edit and execute custom commands to configure microservices.
Author: Keitaro Inc.
Author-email: info@keitaro.com
Classifier: Programming Language :: Python :: 2
Classifier: Programming Language :: Python :: 2.7
Classifier: Programming Language :: Python :: 3
Classifier: Programming Language :: Python :: 3.4
Classifier: Programming Language :: Python :: 3.5
Classifier: Programming Language :: Python :: 3.6
Classifier: Programming Language :: Python :: 3.7
Classifier: Programming Language :: Python :: 3.8
Classifier: Programming Language :: Python :: 3.9
Classifier: Programming Language :: Python :: 3.10
Classifier: Programming Language :: Python :: 3.11
Classifier: Programming Language :: Python :: 3.12
Requires-Dist: click (==7.1.1)
Requires-Dist: click-log (==0.3.2)
Requires-Dist: click-spinner (==0.1.8)
Requires-Dist: cryptography (>=2.9.1,<3.0.0)
Requires-Dist: docker (==4.2.0)
Requires-Dist: flake8 (>=7.0.0,<8.0.0)
Requires-Dist: gitpython (==3.1.41)
Requires-Dist: paramiko (>=2.7.1,<3.0.0)
Requires-Dist: semver (>=2.9.1,<3.0.0)
